snakifit/__init__.py
snakifit/http_client.py
snakifit-0.0.1.dist-info/METADATA
snakifit-0.0.1.dist-info/WHEEL
snakifit-0.0.1.dist-info/top_level.txt
snakifit-0.0.1.dist-info/RECORD
