Metadata-Version: 2.1
Name: snakifit
Version: 0.0.1
Summary: A python http client library inspired by Retrofit, Refit
Home-page: https://github.com/fengb3/http-client-py
Author: fengb3
Author-email: your.email@example.com
Classifier: Programming Language :: Python :: 3
Classifier: License :: OSI Approved :: MIT License
Classifier: Operating System :: OS Independent
Requires-Python: >=3.6
Requires-Dist: requests
Requires-Dist: urllib3
